{
    "WRITING (Original Screenplay)": "Best Original Screenplay",
    "WRITING (Adapted Screenplay)": "Best Adapted Screenplay",
    "VISUAL EFFECTS": "Best Visual Effects",
    "SOUND": "Best Sound",
    "SHORT FILM (Live Action)": "Best Live Action Short Film",
    "SHORT SUBJECT (Live Action)": "Best Live Action Short Film",
    "SHORT FILM (Animated)": "Best Animated Short Film",
    "SHORT SUBJECT (Cartoon)": "Best Animated Short Film",
    "SHORT SUBJECT (Comedy)": "Best Comedic Short Film",
    "SHORT SUBJECT (Color)": "Best Short Film (Color)",
    "SHORT SUBJECT (One-reel)": "Best Short Film (One-Reel)",
    "SHORT SUBJECT (Two-reel)": "Best Short Film (Two-Reel)",
    "PRODUCTION DESIGN": "Best Production Design",
    "BEST PICTURE": "Best Picture",
    "MUSIC (Original Song)": "Best Original Song",
    "MUSIC (Original Score)": "Best Original Score",
    "MAKEUP AND HAIRSTYLING": "Best Makeup and Hairstyling",
    "MAKEUP": "Best Makeup",
    "INTERNATIONAL FEATURE FILM": "Best International Feature Film",
    "FOREIGN LANGUAGE FILM": "Best Foreign Language Film",
    "FILM EDITING": "Best Film Editing",
    "DOCUMENTARY SHORT FILM": "Best Documentary Short Film",
    "DOCUMENTARY FEATURE FILM": "Best Documentary Feature Film",
    "DIRECTING": "Best Director",
    "COSTUME DESIGN": "Best Costume Design",
    "CINEMATOGRAPHY": "Best Cinematography",
    "ANIMATED FEATURE FILM": "Best Animated Feature Film",
    "ACTRESS IN A SUPPORTING ROLE": "Best Supporting Actress",
    "ACTRESS IN A LEADING ROLE": "Best Actress",
    "ACTRESS": "Best Actress",
    "ACTOR IN A SUPPORTING ROLE": "Best Supporting Actor",
    "ACTOR IN A LEADING ROLE": "Best Actor",
    "ACTOR": "Best Actor",
    "SOUND EDITING": "Best Sound Editing",
    "SOUND EFFECTS EDITING": "Best Sound Effects Editing",
    "SOUND RECORDING": "Best Sound Recording",
    "SOUND MIXING": "Best Sound Mixing",
    "ART DIRECTION": "Best Art Direction",
    "ART DIRECTION (Black-and-White)": "Best Art Direction (Black-and-White)",
    "ART DIRECTION (Color)": "Best Art Direction (Color)",
    "ASSISTANT DIRECTOR": "Best Assistant Director",
    "BEST MOTION PICTURE": "Best Picture",
    "CINEMATOGRAPHY (Black-and-White)": "Best Cinematography (Black-and-White)",
    "CINEMATOGRAPHY (Color)": "Best Cinematography (Color)",
    "COSTUME DESIGN (Black-and-White)": "Best Costume Design (Black-and-White)",
    "COSTUME DESIGN (Color)": "Best Costume Design (Color)",
    "DANCE DIRECTION": "Best Dance Direction",
    "DOCUMENTARY": "Best Documentary",
    "DOCUMENTARY (Feature)": "Best Documentary Feature Film",
    "DOCUMENTARY (Short Subject)": "Best Documentary Short Film",
    "HONORARY AWARD": "Honorary Award",
    "IRVING G. THALBERG MEMORIAL AWARD": "Irving G. Thalberg Memorial Award",
    "JEAN HERSHOLT HUMANITARIAN AWARD": "Jean Hersholt Humanitarian Award",
    "MUSIC (Adaptation Score)": "Best Adaptation Score",
    "MUSIC (Music Score of a Dramatic or Comedy Picture)": "Best Music Score of a Dramatic or Comedy Picture",
    "MUSIC (Music Score of a Dramatic Picture)": "Best Music Score of a Dramatic Picture",
    "MUSIC (Music Score--substantially original)": "Best Original Score",
    "MUSIC (Original Dramatic Score)": "Best Original Dramatic Score",
    "MUSIC (Original Music Score)": "Best Original Score",
    "MUSIC (Original Musical or Comedy Score)": "Best Original Musical or Comedy Score",
    "MUSIC (Original Score--for a motion picture [not a musical])": "Best Original Dramatic Score",
    "MUSIC (Original Song Score and Its Adaptation -or- Adaptation Score)": "Best Adaption Score",
    "MUSIC (Original Song Score)": "Best Original Song Score",
    "MUSIC (Score of a Musical Picture--original or adaptation)": "Best Original or Adaption Musical Score",
    "MUSIC (Scoring of a Musical Picture)": "Best Musical Score",
    "MUSIC (Scoring of Music--adaptation or treatment)": "Best Adaption Score",
    "MUSIC (Scoring: Adaptation and Original Song Score)": "Best Original or Adaption Musical Score",
    "MUSIC (Scoring)": "Best Score",
    "MUSIC (Song--Original for the Picture)": "Best Original Song",
    "MUSIC (Song)": "Best Song",
    "OUTSTANDING MOTION PICTURE": "Best Picture",
    "OUTSTANDING PRODUCTION": "Best Picture",
    "SPECIAL ACHIEVEMENT AWARD": "Special Achievement Award",
    "SPECIAL ACHIEVEMENT AWARD (Sound Editing)": "Special Achievement Award (Sound Editing)",
    "SPECIAL ACHIEVEMENT AWARD (Sound Effects Editing)": "Special Achievement Award (Sound Effects Editing)",
    "SPECIAL ACHIEVEMENT AWARD (Sound Effects)": "Special Achievement Award (Sound Effects)",
    "SPECIAL ACHIEVEMENT AWARD (Visual Effects)": "Special Achievement Award (Visual Effects)",
    "SPECIAL AWARD": "Special Award",
    "SPECIAL EFFECTS": "Best Special Effects",
    "SPECIAL VISUAL EFFECTS": "Best Special Visual Effects",
    "UNIQUE AND ARTISTIC PICTURE": "Best Unique and Artistic Picture",
    "WRITING": "Best Screenplay",
    "WRITING (Adaptation)": "Best Adapted Screenplay",
    "WRITING (Motion Picture Story)": "Best Screenplay",
    "WRITING (Original Motion Picture Story)": "Best Original Screenplay",
    "WRITING (Original Story)": "Best Original Story",
    "WRITING (Screenplay Adapted from Other Material)": "Best Adapted Screenplay",
    "WRITING (Screenplay Based on Material from Another Medium)": "Best Adapted Screenplay",
    "WRITING (Screenplay Based on Material Previously Produced or Published)": "Best Adapted Screenplay",
    "Screenplay Written Directly for the Screen--based on factual material or on story material not previously published or produced": "Best Original Screenplay",
    "WRITING (Screenplay Written Directly for the Screen)": "Best Original Screenplay",
    "WRITING (Screenplay--Adapted)": "Best Adapted Screenplay",
    "WRITING (Screenplay--based on material from another medium)": "Best Adapted Screenplay",
    "WRITING (Screenplay)": "Best Screenplay",
    "WRITING (Story and Screenplay--written directly for the screen)": "Best Original Story and Screenplay",
    "Story and Screenplay--based on factual material or material not previously published or produced": "Best Original Screenplay",
    "WRITING (Screenplay Written Directly for the Screen--based on factual material or on story material not previously published or produced)": "Best Original Screenplay",
    "Story and Screenplay--written directly for the screen": "Best Original Screenplay",
    "WRITING (Story and Screenplay)": "Best Story and Screnplay",
    "WRITING (Title Writing)": "Best Title Writing"
}
  